{
  "schemaVersion": 1,
  "id": "getspeed",
  "version": "${version}",
  "name": "getspeed",
  "description": "Log velocity every tick",
  "authors": [
    "GeorgeRNG"
  ],
  "contact": {
    "repo": "https://github.com/georg/getspeed"
  },
  "license": "unlicense",
  "icon": "assets/getspeed/icon.png",
  "environment": "client",
  "entrypoints": {
    "client": [
      "io.github.georgerng.getspeed.client.GetspeedClient"
    ],
    "main": [
      "io.github.georgerng.getspeed.Getspeed"
    ]
  },
  "mixins": [
    "getspeed.mixins.json"
  ],
  "depends": {
    "fabricloader": ">=0.14.19",
    "minecraft": "1.19.4"
  }
}
